llama_index/readers/microsoft_onedrive/__init__.py
llama_index/readers/microsoft_onedrive/base.py
llama_index_readers_microsoft_onedrive-0.4.1.dist-info/METADATA
llama_index_readers_microsoft_onedrive-0.4.1.dist-info/WHEEL
llama_index_readers_microsoft_onedrive-0.4.1.dist-info/licenses/LICENSE
llama_index_readers_microsoft_onedrive-0.4.1.dist-info/RECORD
