Metadata-Version: 2.4
Name: llama-index-readers-microsoft-onedrive
Version: 0.4.1
Summary: llama-index readers microsoft_onedrive integration
Author-email: Your Name <you@example.com>
Maintainer: godwin3737
License-Expression: MIT
License-File: LICENSE
Keywords: microsoft 365,microsoft onedrive,microsoft365,onedrive,onedrive for business,onedrive personal
Requires-Python: <4.0,>=3.9
Requires-Dist: llama-index-core<0.15,>=0.13.0
Requires-Dist: msal<2,>=1.26.0
